{
  "name": "Billy Bones",
  "subtitle": "Keeper of the Map",
  "strength": 6,
  "willpower": 5,
  "quest_value": 1,
  "rarity": "COMMON",
  "ink_cost": 5,
  "author": "Roger Pérez",
  "deck_building_id": "d7d799fb79fd062f882454cc0fc3d4f41da3025e",
  "culture_invariant_id": 540,
  "sort_number": 575,
  "additional_info": [],
  "ink_convertible": true,
  "abilities": [],
  "subtypes": [
    "Storyborn",
    "Alien",
    "Pirate"
  ],
  "flavor_text": "He's after me chest, that fiendish cyborg and his band of cutthroats.",
  "rules_text": "",
  "card_identifier": "104/204 EN 3",
  "image_urls": [
    {
      "height": 2048,
      "url": "https://api.lorcana.ravensburger.com/images/en/set3/cards/1468x2048/104_c882a980e8902d55af64ff71359bdbac738d50b9.jpg"
    },
    {
      "height": 512,
      "url": "https://api.lorcana.ravensburger.com/images/en/set3/cards/367x512/104_215fb35b905f166e38f7094d62414bbe386459c7.jpg"
    }
  ],
  "foil_mask_url": "https://api.lorcana.ravensburger.com/images/en/set3/masks/1468x2048/104_4854098eb50a320ee44b2de4c791232949ce323a.jpg",
  "card_sets": [
    3
  ],
  "magic_ink_colors": [
    "RUBY"
  ],
  "searchable_keywords": [
    "Treasure Planet"
  ]
}