{
  "name": "Aladdin",
  "subtitle": "Intrepid Commander",
  "strength": 1,
  "willpower": 4,
  "quest_value": 2,
  "rarity": "UNCOMMON",
  "ink_cost": 4,
  "author": "Alice Pisoni",
  "deck_building_id": "7e4d253d23bf3576df52bdc66b20bd353eea56dd",
  "culture_invariant_id": 1318,
  "sort_number": 1317,
  "additional_info": [],
  "ink_convertible": true,
  "abilities": [
    "Shift"
  ],
  "subtypes": [
    "Floodborn",
    "Hero",
    "Prince"
  ],
  "flavor_text": "",
  "rules_text": "Shift 2 (You may pay 2 to play this on top of one of your characters named Aladdin.) REMEMBER YOUR TRAINING When you play this character, your characters get +2 this turn.",
  "card_identifier": "119/204 EN 6",
  "image_urls": [
    {
      "height": 2048,
      "url": "https://api.lorcana.ravensburger.com/images/en/set6/119_b052d25aade70e576a9df0d993a82cf1d13d142e.jpg"
    },
    {
      "height": 512,
      "url": "https://api.lorcana.ravensburger.com/images/en/set6/119_c1927e6655398ec3a46de24e09fdcf55753f86be.jpg"
    }
  ],
  "foil_mask_url": "https://api.lorcana.ravensburger.com/images/en/set6/119_fb84052ac436db3a2883d8f90772935978c7b273.jpg",
  "card_sets": [
    6
  ],
  "magic_ink_colors": [
    "RUBY"
  ],
  "searchable_keywords": [
    "Aladdin"
  ]
}