{
  "name": "Jasmine",
  "subtitle": "Disguised",
  "strength": 3,
  "willpower": 3,
  "quest_value": 2,
  "rarity": "COMMON",
  "ink_cost": 3,
  "author": "R. La Barbera / L. Giammichele",
  "deck_building_id": "cd31b0163fb61bbfa637936de6f1c4a2ac6d20d5",
  "culture_invariant_id": 148,
  "sort_number": 148,
  "additional_info": [],
  "ink_convertible": true,
  "abilities": [],
  "subtypes": [
    "Storyborn",
    "Princess"
  ],
  "flavor_text": "Try to understand. I’ve never done a thing on my own. I’ve never had any real friends.. . . I’ve never even been outside the palace walls.",
  "rules_text": "",
  "card_identifier": "148/204 EN 1",
  "image_urls": [
    {
      "height": 2048,
      "url": "https://api.lorcana.ravensburger.com/images/en/set1/cards/1468x2048/148_39c07b108f64d643fcecb0d316ce82e948207982.jpg"
    },
    {
      "height": 512,
      "url": "https://api.lorcana.ravensburger.com/images/en/set1/cards/367x512/148_e5e553e03c9d054966e55869578b9b768173d6dc.jpg"
    }
  ],
  "foil_mask_url": "https://api.lorcana.ravensburger.com/images/en/set1/masks/1468x2048/148_55576141dd8c7233b8a29fe0c1bce779b91b6cf1.jpg",
  "card_sets": [
    1
  ],
  "magic_ink_colors": [
    "SAPPHIRE"
  ],
  "searchable_keywords": [
    "Aladdin"
  ]
}