{
  "name": "The Nokk",
  "subtitle": "Mythical Spirit",
  "strength": 5,
  "willpower": 5,
  "quest_value": 1,
  "rarity": "COMMON",
  "ink_cost": 6,
  "author": "Randy Bishop",
  "deck_building_id": "7bad7251f3367547d9b0c27a5401a24cf5853ffc",
  "culture_invariant_id": 992,
  "sort_number": 1001,
  "additional_info": [],
  "ink_convertible": true,
  "abilities": [],
  "subtypes": [
    "Storyborn",
    "Ally"
  ],
  "flavor_text": "",
  "rules_text": "TURNING TIDES When you play this character, you may move up to 2 damage counters from chosen character to chosen opposing character.",
  "card_identifier": "36/204 EN 5",
  "image_urls": [
    {
      "height": 2048,
      "url": "https://api.lorcana.ravensburger.com/images/en/set5/cards/1468x2048/36_2f6996b80e112f03176a46d9e49e991ace8c79fc.jpg"
    },
    {
      "height": 512,
      "url": "https://api.lorcana.ravensburger.com/images/en/set5/cards/367x512/36_60cd94f11c3399719668b746ea0b763a8f0086f7.jpg"
    }
  ],
  "foil_mask_url": "https://api.lorcana.ravensburger.com/images/en/set5/masks/1468x2048/36_552cebd6b76a95b55240a9704f54da048ac8b2cd.jpg",
  "card_sets": [
    5,
    10
  ],
  "magic_ink_colors": [
    "AMETHYST"
  ],
  "searchable_keywords": [
    "Frozen"
  ]
}