{
  "name": "Bolt",
  "subtitle": "Superdog",
  "strength": 3,
  "willpower": 5,
  "quest_value": 2,
  "rarity": "SUPER",
  "ink_cost": 5,
  "author": "John Loren / Nicholas Kole",
  "deck_building_id": "a31d2bdbf009fa85ab285105f4b19017beef7180",
  "culture_invariant_id": 1437,
  "sort_number": 1435,
  "additional_info": [],
  "ink_convertible": true,
  "abilities": [
    "Shift"
  ],
  "subtypes": [
    "Floodborn",
    "Hero"
  ],
  "flavor_text": "",
  "rules_text": "Shift 3 (You may pay 3 to play this on top of one of your characters named Bolt.) MARK OF POWER Whenever you ready this character, gain 1 lore for each other undamaged character you have in play. BOLT STARE — Banish chosen Illusion character.",
  "card_identifier": "4/204 EN 7",
  "image_urls": [
    {
      "height": 2048,
      "url": "https://api.lorcana.ravensburger.com/images/en/set7/4_a6c4e11c660a169a3bd52d4348c13407ad478831.jpg"
    },
    {
      "height": 512,
      "url": "https://api.lorcana.ravensburger.com/images/en/set7/4_bcc2d9cdc3f6ac8b2a5056cd796478fbaa07b5fb.jpg"
    }
  ],
  "foil_mask_url": "https://api.lorcana.ravensburger.com/images/en/set7/4_cb4469321fe4cfd6ad7a358fadbc7ef101f6ab1f.jpg",
  "card_sets": [
    7
  ],
  "magic_ink_colors": [
    "AMBER",
    "STEEL"
  ],
  "searchable_keywords": [
    "Bolt"
  ]
}