{
  "name": "Dalmatian Puppy",
  "subtitle": "Tail Wagger",
  "strength": 2,
  "willpower": 3,
  "quest_value": 1,
  "rarity": "COMMON",
  "ink_cost": 2,
  "author": "Kapik",
  "deck_building_id": "41a059413bf3c6cc52013cb2a2306150864300be",
  "deck_building_limit": 99,
  "culture_invariant_id": 438,
  "sort_number": 472,
  "additional_info": [],
  "ink_convertible": true,
  "abilities": [],
  "subtypes": [
    "Storyborn",
    "Puppy"
  ],
  "flavor_text": "First they steal your heart. Then they steal your chair.",
  "rules_text": "WHERE DID THEY ALL COME FROM? You may have up to 99 copies of Dalmatian Puppy – Tail Wagger in your deck.",
  "card_identifier": "4c/204 EN 3",
  "image_urls": [
    {
      "height": 2048,
      "url": "https://api.lorcana.ravensburger.com/images/en/set3/cards/1468x2048/4c_fc2b4f1d17aaafa16be7a54aeded7dbb51fcf76f.jpg"
    },
    {
      "height": 512,
      "url": "https://api.lorcana.ravensburger.com/images/en/set3/cards/367x512/4c_dcca4d18760ae8ce9f9d012a6654cebffcd34ee9.jpg"
    }
  ],
  "foil_mask_url": "https://api.lorcana.ravensburger.com/images/en/set3/masks/1468x2048/4c_52af5e1b343888e8129e7c963cd90da3da400eb1.jpg",
  "card_sets": [
    3
  ],
  "magic_ink_colors": [
    "AMBER"
  ],
  "searchable_keywords": [
    "101 Dalmatians"
  ]
}