{
  "name": "Anna",
  "subtitle": "Magical Mission",
  "strength": 3,
  "willpower": 6,
  "quest_value": 2,
  "rarity": "RARE",
  "ink_cost": 6,
  "author": "Luigi Aimè",
  "deck_building_id": "f7597462c9c984bf95b7fa001b581e598fd47c38",
  "culture_invariant_id": 1736,
  "sort_number": 1736,
  "additional_info": [],
  "ink_convertible": true,
  "abilities": [
    "Shift",
    "Support"
  ],
  "subtypes": [
    "Floodborn",
    "Hero",
    "Queen",
    "Sorcerer"
  ],
  "flavor_text": "",
  "rules_text": "Shift 4 (You may pay 4 to play this on top of one of your characters named Anna.) Support (Whenever this character quests, you may add their to another chosen character's this turn.) COORDINATED PLAN Whenever this character quests, if you have a character named Elsa in play, you may draw a card.",
  "card_identifier": "72/204 EN 8",
  "image_urls": [
    {
      "height": 2048,
      "url": "https://api.lorcana.ravensburger.com/images/en/set8/cards/1468x2048/72_9ee84ec10a2d5ae8462eefdf386b37fb99e3cf59.jpg"
    },
    {
      "height": 512,
      "url": "https://api.lorcana.ravensburger.com/images/en/set8/cards/367x512/72_81e4257f2061206111dd3fe665ea41eaafbc3fb9.jpg"
    }
  ],
  "foil_mask_url": "https://api.lorcana.ravensburger.com/images/en/set8/masks/1468x2048/72_b7eb2b1541ade7ebf84b4c3da0d259521cade888.jpg",
  "card_sets": [
    8,
    10
  ],
  "magic_ink_colors": [
    "AMETHYST",
    "SAPPHIRE"
  ],
  "searchable_keywords": [
    "Frozen"
  ]
}