{
  "name": "Taffyta Muttonfudge",
  "subtitle": "Rücksichtslose Rivalin",
  "strength": 2,
  "willpower": 2,
  "quest_value": 2,
  "rarity": "UNCOMMON",
  "ink_cost": 2,
  "author": "Koni",
  "deck_building_id": "b1547de58e411188b70e13229d5f6d68cee6482d",
  "culture_invariant_id": 1059,
  "sort_number": 1067,
  "additional_info": [],
  "ink_convertible": true,
  "abilities": [],
  "subtypes": [
    "Sagengestalt",
    "Verbündeter",
    "Rennfahrer"
  ],
  "flavor_text": "Kein Glimmer kann mit mir mithalten. Du kannst auch gleich aufgeben.",
  "rules_text": "",
  "card_identifier": "103/204 DE 5",
  "image_urls": [
    {
      "height": 2048,
      "url": "https://api.lorcana.ravensburger.com/images/de/set5/cards/1468x2048/103_b471d73a4e4074a5d219ab63054cb1134dc7a588.jpg"
    },
    {
      "height": 512,
      "url": "https://api.lorcana.ravensburger.com/images/de/set5/cards/367x512/103_ed3d5aeaafc74f73ec08f48ee49beacb2792c1d2.jpg"
    }
  ],
  "foil_mask_url": "https://api.lorcana.ravensburger.com/images/de/set5/masks/1468x2048/103_f9830d61e2ffdaec33c74592577fec9e6ea994bb.jpg",
  "card_sets": [
    5
  ],
  "magic_ink_colors": [
    "RUBY"
  ],
  "searchable_keywords": [
    "Ralph reichts",
    "Wreck It Ralph"
  ]
}