{
  "name": "B.E.N.",
  "subtitle": "Exzentrischer Roboter",
  "strength": 4,
  "willpower": 3,
  "quest_value": 2,
  "rarity": "COMMON",
  "ink_cost": 4,
  "author": "Gwawi",
  "deck_building_id": "aa97f4df72681860790f4df212f77ab3bf9a7239",
  "culture_invariant_id": 1336,
  "sort_number": 1335,
  "additional_info": [],
  "ink_convertible": true,
  "abilities": [
    "Unterstützen"
  ],
  "subtypes": [
    "Sagengestalt",
    "Verbündeter",
    "Roboter",
    "Pirat"
  ],
  "flavor_text": "",
  "rules_text": "Unterstützen (Jedes Mal, wenn dieser Charakter erkundet, darfst du seine in diesem Zug zur eines anderen Charakters deiner Wahl addieren.)",
  "card_identifier": "137/204 DE 6",
  "image_urls": [
    {
      "height": 2048,
      "url": "https://api.lorcana.ravensburger.com/images/de/set6/cards/1468x2048/137_3e7bea2ed807407804e6c017d9855a80c2df3a59.jpg"
    },
    {
      "height": 512,
      "url": "https://api.lorcana.ravensburger.com/images/de/set6/cards/367x512/137_a1ba5521fcf67d3fde19ab4f8b21fbd1c32bdf3a.jpg"
    }
  ],
  "foil_mask_url": "https://api.lorcana.ravensburger.com/images/de/set6/masks/1468x2048/137_b6b15e5ba03ab594150e88415c3a816558e63096.jpg",
  "card_sets": [
    6,
    10
  ],
  "magic_ink_colors": [
    "SAPPHIRE"
  ],
  "searchable_keywords": [
    "Treasure Planet",
    "Der Schatzplanet"
  ]
}