{
  "name": "Die Königin",
  "subtitle": "Wahrsagerin",
  "strength": 3,
  "willpower": 3,
  "quest_value": 1,
  "rarity": "LEGENDARY",
  "ink_cost": 3,
  "author": "Mel Milton",
  "deck_building_id": "25872e2f6a7538f1bad704261005852bd2804752",
  "culture_invariant_id": 847,
  "sort_number": 856,
  "additional_info": [],
  "ink_convertible": true,
  "abilities": [],
  "subtypes": [
    "Traumgestalt",
    "Schurkin",
    "Königin",
    "Magierin"
  ],
  "flavor_text": "",
  "rules_text": "DAS ZAUBERBUCH BEFRAGEN – Schaue dir die obersten 4 Karten deines Decks an. Du darfst 1 Gegenstandskarte daraus aufdecken und auf deine Hand nehmen. Falls dieser Gegenstand 3 oder weniger kostet, darfst du ihn stattdessen kostenlos und erschöpft ausspielen. Lege die restlichen Karten in beliebiger Reihenfolge unter dein Deck.",
  "card_identifier": "156/204 DE 4",
  "image_urls": [
    {
      "height": 2048,
      "url": "https://api.lorcana.ravensburger.com/images/de/set4/cards/1468x2048/156_37c0cefcfae82630fae9b445f7052a35a9f282fb.jpg"
    },
    {
      "height": 512,
      "url": "https://api.lorcana.ravensburger.com/images/de/set4/cards/367x512/156_8057bfe3acf80e8003a8144f00fa75c03e1e3724.jpg"
    }
  ],
  "foil_mask_url": "https://api.lorcana.ravensburger.com/images/de/set4/masks/1468x2048/156_e14c0708f540aef2b1e4811c428e3e161433a23d.jpg",
  "card_sets": [
    4
  ],
  "magic_ink_colors": [
    "SAPPHIRE"
  ],
  "searchable_keywords": [
    "Schneewittchen und die sieben Zwerge",
    "Snow White"
  ]
}