{
  "name": "Benja",
  "subtitle": "Wächter des Drachenjuwels",
  "strength": 2,
  "willpower": 3,
  "quest_value": 2,
  "rarity": "COMMON",
  "ink_cost": 3,
  "author": "Grace Tran",
  "deck_building_id": "91f61fcecd0f1ec5ba977e234746108beae719d3",
  "culture_invariant_id": 390,
  "sort_number": 414,
  "additional_info": [],
  "ink_convertible": true,
  "abilities": [],
  "subtypes": [
    "Sagengestalt",
    "Mentor",
    "König"
  ],
  "flavor_text": "Verwechsle Kühnheit nicht mit Können.",
  "rules_text": "WIR HABEN EINE WAHL Wenn du diesen Charakter ausspielst, darfst du einen Gegenstand deiner Wahl verbannen.",
  "card_identifier": "174/204 DE 2",
  "image_urls": [
    {
      "height": 2048,
      "url": "https://api.lorcana.ravensburger.com/images/de/set2/174_66b3f5b03c715c1dd891009ac3ddad7e711f2cb5.jpg"
    },
    {
      "height": 512,
      "url": "https://api.lorcana.ravensburger.com/images/de/set2/174_b7758995264d62a9bf6a1aa49a120180f58efc05.jpg"
    }
  ],
  "foil_mask_url": "https://api.lorcana.ravensburger.com/images/de/set2/174_bf9bc5ffba592ede9c3ecada50e78e9d1fc884f8.jpg",
  "card_sets": [
    2,
    9
  ],
  "magic_ink_colors": [
    "STEEL"
  ],
  "searchable_keywords": [
    "Raya und der letzte Drache",
    "Raya and the Last Dragon"
  ]
}