{
  "name": "Bolt",
  "subtitle": "Starrköpfiger Hund",
  "strength": 1,
  "willpower": 3,
  "quest_value": 1,
  "rarity": "COMMON",
  "ink_cost": 2,
  "author": "Brian Weisz",
  "deck_building_id": "8e6b0a691fd08092d8dcbaaa348d77b450f4795e",
  "culture_invariant_id": 1617,
  "sort_number": 1615,
  "additional_info": [],
  "ink_convertible": true,
  "abilities": [],
  "subtypes": [
    "Sagengestalt",
    "Held"
  ],
  "flavor_text": "So wie’s aussieht, ist die harte Tour nötig.",
  "rules_text": "ES GIBT KEIN ZURÜCK Jedes Mal, wenn dieser Charakter erkundet, falls er unbeschädigt ist, darfst du 1 Karte ziehen. Wähle danach 1 Karte aus deiner Hand und wirf sie ab.",
  "card_identifier": "184/204 DE 7",
  "image_urls": [
    {
      "height": 2048,
      "url": "https://api.lorcana.ravensburger.com/images/de/set7/cards/1468x2048/184_75af1cedd74293caf4f9db63773b823d90b1636c.jpg"
    },
    {
      "height": 512,
      "url": "https://api.lorcana.ravensburger.com/images/de/set7/cards/367x512/184_572f1c69dbd061a7dcf3b638b741d9d6f6b96f20.jpg"
    }
  ],
  "foil_mask_url": "https://api.lorcana.ravensburger.com/images/de/set7/masks/1468x2048/184_c6735220d44f6d525c3f071625391c0c135fe8e4.jpg",
  "card_sets": [
    7,
    10
  ],
  "magic_ink_colors": [
    "STEEL"
  ],
  "searchable_keywords": [
    "Bolt"
  ]
}