{
  "name": "Penny",
  "subtitle": "Bolts Frauchen",
  "strength": 1,
  "willpower": 2,
  "quest_value": 2,
  "rarity": "UNCOMMON",
  "ink_cost": 2,
  "author": "Aisha Durmagambetova",
  "deck_building_id": "411deec2bc09d6d9bad7ac874b976b9ef4264678",
  "culture_invariant_id": 1454,
  "sort_number": 1452,
  "additional_info": [],
  "ink_convertible": true,
  "abilities": [],
  "subtypes": [
    "Sagengestalt",
    "Verbündeter"
  ],
  "flavor_text": "",
  "rules_text": "EWIGE LOYALITÄT Wenn du diesen Charakter ausspielst, darfst du bis zu 2 Schaden von einem Charakter deiner Wahl entfernen. Er erhält bis zu Beginn deines nächsten Zuges Robust +1. (Reduziere jeglichen Schaden, der jenem Charakter zugefügt wird, um 1.)",
  "card_identifier": "21/204 DE 7",
  "image_urls": [
    {
      "height": 2048,
      "url": "https://api.lorcana.ravensburger.com/images/de/set7/21_4c39225473565f57518f7ae22a97c644423df200.jpg"
    },
    {
      "height": 512,
      "url": "https://api.lorcana.ravensburger.com/images/de/set7/21_403e0a725f7ceb994d8f8825393c4d5dd82a100e.jpg"
    }
  ],
  "foil_mask_url": "https://api.lorcana.ravensburger.com/images/de/set7/21_212b605c210e0b12d67086fc7529a65f5734ea7b.jpg",
  "card_sets": [
    7,
    10
  ],
  "magic_ink_colors": [
    "AMBER",
    "STEEL"
  ],
  "searchable_keywords": [
    "Bolt"
  ]
}