{
  "name": "Dschinni",
  "subtitle": "Stets eindrucksvoll",
  "strength": 2,
  "willpower": 3,
  "quest_value": 1,
  "rarity": "COMMON",
  "ink_cost": 2,
  "author": "Matt Chapman",
  "deck_building_id": "9b79f3f2091291724aca48822463ad7cac92b860",
  "culture_invariant_id": 77,
  "sort_number": 77,
  "additional_info": [],
  "ink_convertible": true,
  "abilities": [],
  "subtypes": [
    "Traumgestalt",
    "Verbündeter"
  ],
  "flavor_text": "Du kannst dir fast alles wünschen! Willst du die kurze Version oder soll ich dir das ganze Lied und den Tanz geben?",
  "rules_text": "",
  "card_identifier": "77/204 DE 1",
  "image_urls": [
    {
      "height": 2048,
      "url": "https://api.lorcana.ravensburger.com/images/de/set1/77_862d583162bd62d2549e04df2be0899c70842ad4.jpg"
    },
    {
      "height": 512,
      "url": "https://api.lorcana.ravensburger.com/images/de/set1/77_ce3176123aabd1c444c8388a5a696aab5bd2fbec.jpg"
    }
  ],
  "foil_mask_url": "https://api.lorcana.ravensburger.com/images/de/set1/77_22d8ad0730cd8e1077ad68f057c9263dad05b9ae.jpg",
  "card_sets": [
    1
  ],
  "magic_ink_colors": [
    "EMERALD"
  ],
  "searchable_keywords": [
    "Aladdin"
  ]
}