{
  "name": "Porta Blindata",
  "rarity": "COMMON",
  "ink_cost": 4,
  "author": "Nicolas Ky",
  "deck_building_id": "d4e40d3f6a1cb410ae20b81b5ccb4c8c6304b4ad",
  "culture_invariant_id": 603,
  "sort_number": 638,
  "additional_info": [],
  "ink_convertible": true,
  "abilities": [],
  "subtypes": [],
  "flavor_text": "Solo Paperone sa di <questo> caveau. E non ha intenzione di cambiare le cose.",
  "rules_text": "SIGILLATO I tuoi luoghi e i tuoi personaggi in un luogo ottengono Resistere +1. (Il danno che gli viene inflitto è ridotto di 1.)",
  "card_identifier": "167/204 IT 3",
  "image_urls": [
    {
      "height": 2048,
      "url": "https://api.lorcana.ravensburger.com/images/it/set3/cards/1468x2048/167_8b290a0657fc89240810ff8f6abcbe2434ada0ec.jpg"
    },
    {
      "height": 512,
      "url": "https://api.lorcana.ravensburger.com/images/it/set3/cards/367x512/167_9509e72ff3e3594cbcc894fc1453ff642d6aa48d.jpg"
    }
  ],
  "foil_mask_url": "https://api.lorcana.ravensburger.com/images/it/set3/masks/1468x2048/167_d61e409a27ce7485baaa0529656283be3ab6c8de.jpg",
  "card_sets": [
    3
  ],
  "magic_ink_colors": [
    "SAPPHIRE"
  ],
  "searchable_keywords": [
    "Ducktales"
  ]
}