{
  "name": "Polvere di Fata",
  "rarity": "UNCOMMON",
  "ink_cost": 4,
  "author": "Ellie Horie / Mara Tango",
  "deck_building_id": "81bfe47645b7451e9719f784418d39de85304651",
  "culture_invariant_id": 1266,
  "sort_number": 1265,
  "additional_info": [],
  "ink_convertible": false,
  "abilities": [],
  "subtypes": [],
  "flavor_text": "",
  "rules_text": "UN PO' DI FANTASIA , 2 — Un personaggio a tua scelta ottiene Sfidante +2 e Sfuggente fino all'inizio del tuo prossimo turno. (Riceve +2 mentre sta sfidando. Solo altri personaggi con Sfuggente possono sfidarlo.)",
  "card_identifier": "67/204 IT 6",
  "image_urls": [
    {
      "height": 2048,
      "url": "https://api.lorcana.ravensburger.com/images/it/set6/cards/1468x2048/67_89715434fdd1421389ecd774f68bf550a95f9c65.jpg"
    },
    {
      "height": 512,
      "url": "https://api.lorcana.ravensburger.com/images/it/set6/cards/367x512/67_d45e1104c641db7ff30e627aacf4a0ea767e0b07.jpg"
    }
  ],
  "foil_mask_url": "https://api.lorcana.ravensburger.com/images/it/set6/masks/1468x2048/67_bfa1c063946acfe65d633a2e917f1af0f709274b.jpg",
  "card_sets": [
    6
  ],
  "magic_ink_colors": [
    "AMETHYST"
  ],
  "searchable_keywords": [
    "Peter Pan",
    "Le avventure di Peter Pan"
  ]
}