{
  "name": "Cruella De Vil",
  "subtitle": "Perfectly Wretched",
  "strength": 4,
  "willpower": 3,
  "quest_value": 2,
  "rarity": "UNCOMMON",
  "ink_cost": 5,
  "author": "GusGadget / Leonardo Giammichele",
  "deck_building_id": "cee03f2073c8ac1d8da9f9dce64776138f2df77a",
  "culture_invariant_id": 361,
  "sort_number": 385,
  "additional_info": [],
  "ink_convertible": true,
  "abilities": [
    "Shift"
  ],
  "subtypes": [
    "Floodborn",
    "Villain"
  ],
  "flavor_text": "It's ink couture, darling. I wear only the best!",
  "rules_text": "Shift 3 (You may pay 3 to play this on top of one of your characters named Cruella De Vil.) OH, NO YOU DON'T Whenever this character quests, chosen opposing character gets -2 this turn.",
  "card_identifier": "145/204 EN 2",
  "image_urls": [
    {
      "height": 2048,
      "url": "https://api.lorcana.ravensburger.com/images/en/set2/145_5ff79f977b9cdef1b1dac6d9d843d683d110436b.jpg"
    },
    {
      "height": 512,
      "url": "https://api.lorcana.ravensburger.com/images/en/set2/145_5b395321f968b2216345f2e3aa842ede1ca903e5.jpg"
    }
  ],
  "foil_mask_url": "https://api.lorcana.ravensburger.com/images/en/set2/145_43c2d063797c67d969b914070d675f1861012f84.jpg",
  "card_sets": [
    2
  ],
  "magic_ink_colors": [
    "SAPPHIRE"
  ],
  "searchable_keywords": [
    "101 Dalmatians",
    "La carica dei 101"
  ]
}