{
  "name": "Topolino",
  "subtitle": "Direttore della Banda",
  "strength": 2,
  "willpower": 5,
  "quest_value": 1,
  "rarity": "UNCOMMON",
  "ink_cost": 4,
  "author": "Filipe Laurentino",
  "deck_building_id": "db76b4423fa5a9cc7723c556824d7eeed5c20bf0",
  "culture_invariant_id": 706,
  "sort_number": 715,
  "additional_info": [],
  "ink_convertible": true,
  "abilities": [
    "Aiutante"
  ],
  "subtypes": [
    "Classico",
    "Eroe"
  ],
  "flavor_text": "",
  "rules_text": "Aiutante (Ogni volta che questo personaggio va all'avventura, puoi aggiungere la sua alla di un altro personaggio a tua scelta per questo turno.) ATTACCARE IL PEZZO Quando giochi questo personaggio, un personaggio a tua scelta ottiene Aiutante per questo turno.",
  "card_identifier": "15/204 IT 4",
  "image_urls": [
    {
      "height": 2048,
      "url": "https://api.lorcana.ravensburger.com/images/it/set4/cards/1468x2048/15_8e8c4e7201fd43792ff3ef1774d2db4a1a471ba6.jpg"
    },
    {
      "height": 512,
      "url": "https://api.lorcana.ravensburger.com/images/it/set4/cards/367x512/15_5af23eeb9a749590c433f42f4fff62f7b80e6c46.jpg"
    }
  ],
  "foil_mask_url": "https://api.lorcana.ravensburger.com/images/it/set4/masks/1468x2048/15_05fcc7ad710ec704c44275730b9063397cd7e86d.jpg",
  "card_sets": [
    4,
    11
  ],
  "magic_ink_colors": [
    "AMBER"
  ]
}