{
  "name": "Aurora",
  "subtitle": "Bellezza Risvegliata",
  "strength": 1,
  "willpower": 4,
  "quest_value": 2,
  "rarity": "ENCHANTED",
  "ink_cost": 3,
  "author": "Viv Tanner",
  "deck_building_id": "2ea925b3bcd4e58c5bd1d5bb775db0d24bf1d993",
  "culture_invariant_id": 1638,
  "sort_number": 1635,
  "additional_info": [],
  "ink_convertible": true,
  "abilities": [
    "Melodioso"
  ],
  "subtypes": [
    "Classico",
    "Eroe",
    "Principessa"
  ],
  "flavor_text": "",
  "rules_text": "Melodioso 5 (Questo personaggio conta come di costo 5 per cantare le canzoni.) SOGNI D'ORO Ogni volta che rimuovi 1 o più danni da un personaggio, prepara questo personaggio. Non può andare all'avventura o sfidare per il resto di questo turno.",
  "card_identifier": "205/204 IT 7",
  "image_urls": [
    {
      "height": 2048,
      "url": "https://api.lorcana.ravensburger.com/images/it/set7/cards/1468x2048/205_26f40703e279b18cbaf3fd9d8eb47db077f89c3f.jpg"
    },
    {
      "height": 512,
      "url": "https://api.lorcana.ravensburger.com/images/it/set7/cards/367x512/205_23c7785c913020e0d520585266b9bf612460dfda.jpg"
    }
  ],
  "foil_mask_url": "https://api.lorcana.ravensburger.com/images/it/set7/masks/1468x2048/205_ec69a8539b47d7354fb10b2bab74aac450ae5623.jpg",
  "foil_type": "VerticalWave",
  "card_sets": [
    7
  ],
  "magic_ink_colors": [
    "AMBER"
  ],
  "searchable_keywords": [
    "Sleeping Beauty",
    "La bella addormentata nel bosco"
  ]
}