{
  "name": "Stitch",
  "subtitle": "Nuovo Cagnolino",
  "strength": 2,
  "willpower": 2,
  "quest_value": 1,
  "rarity": "COMMON",
  "ink_cost": 1,
  "author": "Alex Accorsi",
  "deck_building_id": "409ccaff640db6b84e1ee98232013e2c9c43b5d1",
  "culture_invariant_id": 22,
  "sort_number": 22,
  "additional_info": [],
  "ink_convertible": true,
  "abilities": [],
  "subtypes": [
    "Classico",
    "Eroe",
    "Alieno"
  ],
  "flavor_text": "Lilo: David! Questo è il mio nuovo cane!%David: Auwe! Sicura che è un cane?%Lilo: Uh-huh, era un collie prima che lo mettesse sotto un camion.",
  "rules_text": "",
  "card_identifier": "22/204 IT 1",
  "image_urls": [
    {
      "height": 2048,
      "url": "https://api.lorcana.ravensburger.com/images/it/set1/cards/1468x2048/22_d97bdd90b0e3fdac19aecfe0d273384007040ec0.jpg"
    },
    {
      "height": 512,
      "url": "https://api.lorcana.ravensburger.com/images/it/set1/cards/367x512/22_d88b8843ed16bf6b2790660f2016c32cc45ca078.jpg"
    }
  ],
  "foil_mask_url": "https://api.lorcana.ravensburger.com/images/it/set1/masks/1468x2048/22_f2f10ed429d36acc3b45167ca09973fade09a1aa.jpg",
  "card_sets": [
    1,
    11
  ],
  "magic_ink_colors": [
    "AMBER"
  ],
  "searchable_keywords": [
    "Lilo & Stitch",
    "Lilo and Stitch"
  ]
}