{
  "name": "Ursula",
  "subtitle": "Vanessa",
  "strength": 1,
  "willpower": 4,
  "quest_value": 1,
  "rarity": "COMMON",
  "ink_cost": 2,
  "author": "Angela Simpson",
  "deck_building_id": "4e8aaca4272863b70bf21a78240c97ccad2e3ce5",
  "culture_invariant_id": 716,
  "sort_number": 726,
  "additional_info": [],
  "ink_convertible": true,
  "abilities": [
    "Melodioso"
  ],
  "subtypes": [
    "Classico",
    "Cattivo",
    "Incantatore"
  ],
  "flavor_text": "Questa magia avrà sicuramente effetto.",
  "rules_text": "Melodioso 4 (Questo personaggio conta come di costo 4 per cantare le canzoni.)",
  "card_identifier": "25/204 IT 4",
  "image_urls": [
    {
      "height": 2048,
      "url": "https://api.lorcana.ravensburger.com/images/it/set4/cards/1468x2048/25_f9778275886533c703e483a75bd1416d7c335534.jpg"
    },
    {
      "height": 512,
      "url": "https://api.lorcana.ravensburger.com/images/it/set4/cards/367x512/25_16ae1675f8a8bc0d597c58240e318541b23c8a10.jpg"
    }
  ],
  "foil_mask_url": "https://api.lorcana.ravensburger.com/images/it/set4/masks/1468x2048/25_74490c619d54abc5199860b502693b8ca0f5553e.jpg",
  "card_sets": [
    4
  ],
  "magic_ink_colors": [
    "AMBER"
  ],
  "searchable_keywords": [
    "Little Mermaid",
    "La Sirenetta"
  ]
}