{
  "name": "Fido",
  "subtitle": "Segugio Leale",
  "strength": 2,
  "willpower": 2,
  "quest_value": 1,
  "rarity": "COMMON",
  "ink_cost": 2,
  "author": "Yu Nguyễn",
  "deck_building_id": "59fb789b94c97942a564b6c0fd20a35b436b07c6",
  "culture_invariant_id": 1439,
  "sort_number": 1437,
  "additional_info": [],
  "ink_convertible": true,
  "abilities": [
    "Aiutante"
  ],
  "subtypes": [
    "Classico",
    "Alleato"
  ],
  "flavor_text": "Come il mio vecchio nonno Fedele diceva sempre, risparmia le energie per quando servono davvero.",
  "rules_text": "Aiutante (Ogni volta che questo personaggio va all’avventura, puoi aggiungere la sua alla di un altro personaggio a tua scelta per questo turno.)",
  "card_identifier": "6/204 IT 7",
  "image_urls": [
    {
      "height": 2048,
      "url": "https://api.lorcana.ravensburger.com/images/it/set7/cards/1468x2048/6_fa835e915e4e3d31409f3834b2a153d7c323dbd2.jpg"
    },
    {
      "height": 512,
      "url": "https://api.lorcana.ravensburger.com/images/it/set7/cards/367x512/6_f3d6b8882aeadad79db1a10cb3c38c09d04a94b7.jpg"
    }
  ],
  "foil_mask_url": "https://api.lorcana.ravensburger.com/images/it/set7/masks/1468x2048/6_6bc5ba718c9eb7e026ac6a466cbb66a814e4487f.jpg",
  "card_sets": [
    7,
    10
  ],
  "magic_ink_colors": [
    "AMBER"
  ],
  "searchable_keywords": [
    "Lilli e il vagabondo",
    "Lady and the Tramp"
  ]
}