{
  "name": "Wer's findet, darf's behalten",
  "rarity": "UNCOMMON",
  "ink_cost": 5,
  "author": "Andy Estrada / Stefano Zanchi",
  "deck_building_id": "5e2657fa5dbffd004f504784ce267a28e50d742c",
  "culture_invariant_id": 1016,
  "sort_number": 1025,
  "additional_info": [],
  "ink_convertible": true,
  "abilities": [],
  "subtypes": [],
  "flavor_text": "Drei Wünsche, kommt sofort!%—Jago",
  "rules_text": "Ziehe 3 Karten.",
  "card_identifier": "60/204 DE 5",
  "image_urls": [
    {
      "height": 2048,
      "url": "https://api.lorcana.ravensburger.com/images/de/set5/60_6be5063bfdaf39ecf79bc30f58febd1e0788502b.jpg"
    },
    {
      "height": 512,
      "url": "https://api.lorcana.ravensburger.com/images/de/set5/60_a48e1e9cfae4773a926ef531964a8b880371c16a.jpg"
    }
  ],
  "foil_mask_url": "https://api.lorcana.ravensburger.com/images/de/set5/60_e547c0d51238cc4bd1562cfbd2ea141f62b89e28.jpg",
  "card_sets": [
    5
  ],
  "magic_ink_colors": [
    "AMETHYST"
  ],
  "searchable_keywords": [
    "Aladdin"
  ]
}