{
  "name": "Gardes cartes",
  "subtitle": "Troupes royales",
  "strength": 1,
  "willpower": 2,
  "quest_value": 1,
  "rarity": "COMMON",
  "ink_cost": 1,
  "author": "Kamil Murzyn",
  "deck_building_id": "dcb1ec98a56ada4be8acd345b0b77737465de130",
  "culture_invariant_id": 1562,
  "sort_number": 1560,
  "additional_info": [],
  "ink_convertible": true,
  "abilities": [],
  "subtypes": [
    "Storyborn",
    "Allié"
  ],
  "flavor_text": "Le Trois de Cœur brandit sa lance et murmura: Quand les autres tombent, un soldat de la Reine, lui, reste debout.",
  "rules_text": "PRENDRE POSITION Tant qu'un personnage a au moins un dommage, ce personnage-ci gagne +2.",
  "card_identifier": "129/204 FR 7",
  "image_urls": [
    {
      "height": 2048,
      "url": "https://api.lorcana.ravensburger.com/images/fr/set7/129_eb14bfb95c7cdcc032b010b2cc37e819ac8f4c21.jpg"
    },
    {
      "height": 512,
      "url": "https://api.lorcana.ravensburger.com/images/fr/set7/129_faf501b6487620f45540a758c99c58f706e7327d.jpg"
    }
  ],
  "foil_mask_url": "https://api.lorcana.ravensburger.com/images/fr/set7/129_faa714fe37a75ae1d34f00d4123c908f6617d138.jpg",
  "card_sets": [
    7
  ],
  "magic_ink_colors": [
    "RUBY"
  ],
  "searchable_keywords": [
    "Alice au Pays des Merveilles",
    "Alice in Wonderland"
  ]
}