{
  "name": "Balthazar Picsou",
  "subtitle": "Amateur d'antiquités",
  "strength": 5,
  "willpower": 5,
  "quest_value": 2,
  "rarity": "RARE",
  "ink_cost": 4,
  "author": "Cam Kendell",
  "deck_building_id": "1262f10b12ccaed7c5ea1884842b08062ba5d6b9",
  "culture_invariant_id": 1096,
  "sort_number": 1105,
  "additional_info": [],
  "ink_convertible": false,
  "abilities": [],
  "subtypes": [
    "Storyborn",
    "Héros"
  ],
  "flavor_text": "La pièce secrète devrait être juste ici ! Ah, je n'arrive pas à croire que j'ai dépensé un sou pour cette carte.",
  "rules_text": "",
  "card_identifier": "140/204 FR 5",
  "image_urls": [
    {
      "height": 2048,
      "url": "https://api.lorcana.ravensburger.com/images/fr/set5/140_fd86678432ee598d4348b78f4d9ef6919489467e.jpg"
    },
    {
      "height": 512,
      "url": "https://api.lorcana.ravensburger.com/images/fr/set5/140_d261e6e92c1e878d39e0e7ad6503134e0b648688.jpg"
    }
  ],
  "foil_mask_url": "https://api.lorcana.ravensburger.com/images/fr/set5/140_92ac90e35b3d46d9a7158ff2e9bbd69a8d9d397d.jpg",
  "card_sets": [
    5
  ],
  "magic_ink_colors": [
    "SAPPHIRE"
  ],
  "searchable_keywords": [
    "Ducktales",
    "La Bande à Picsou"
  ]
}