{
  "name": "Arthur",
  "subtitle": "Moustique",
  "strength": 2,
  "willpower": 2,
  "quest_value": 2,
  "rarity": "UNCOMMON",
  "ink_cost": 2,
  "author": "Kasia Brzezinska",
  "deck_building_id": "ea4fccb865562f690c50de02ff9e7d716e781197",
  "culture_invariant_id": 1146,
  "sort_number": 1155,
  "additional_info": [],
  "ink_convertible": true,
  "abilities": [],
  "subtypes": [
    "Storyborn",
    "Héros"
  ],
  "flavor_text": "Ce petit est plein de feu. Il est énergique et se donne corps et âme à tout ce qu’il entreprend.%— Merlin",
  "rules_text": "",
  "card_identifier": "190/204 FR 5",
  "image_urls": [
    {
      "height": 2048,
      "url": "https://api.lorcana.ravensburger.com/images/fr/set5/190_29fcc9f234b526cd48548b5a62593ad80732aa24.jpg"
    },
    {
      "height": 512,
      "url": "https://api.lorcana.ravensburger.com/images/fr/set5/190_6a11d021d33d268a5395e6bf6a83d8fdb3f40e1d.jpg"
    }
  ],
  "foil_mask_url": "https://api.lorcana.ravensburger.com/images/fr/set5/190_29f170707d633b40742b508c30622ed313170e89.jpg",
  "card_sets": [
    5
  ],
  "magic_ink_colors": [
    "STEEL"
  ],
  "searchable_keywords": [
    "Sword in the Stone",
    "Merlin l'Enchanteur"
  ]
}