{
  "name": "Timide",
  "subtitle": "Grand sentimental",
  "strength": 2,
  "willpower": 5,
  "quest_value": 3,
  "rarity": "UNCOMMON",
  "ink_cost": 4,
  "author": "Kendall Hale",
  "deck_building_id": "b95e7b9108cbc2a1fc2700fda19b86520ee93c3e",
  "culture_invariant_id": 217,
  "sort_number": 241,
  "additional_info": [],
  "ink_convertible": true,
  "abilities": [],
  "subtypes": [
    "Storyborn",
    "Allié",
    "Sept Nains"
  ],
  "flavor_text": "La vie est plus douce quand on a des amis.",
  "rules_text": "OH... Vous devez avoir un autre personnage Sept Nains en jeu pour pouvoir envoyer ce personnage à l'aventure.",
  "card_identifier": "1/204 FR 2",
  "image_urls": [
    {
      "height": 2048,
      "url": "https://api.lorcana.ravensburger.com/images/fr/set2/cards/1468x2048/1_ae2a81aeef1f9774377ca95c5474a69f0a218c09.jpg"
    },
    {
      "height": 512,
      "url": "https://api.lorcana.ravensburger.com/images/fr/set2/cards/367x512/1_d29a12d021a8595da0e76b4f717e1a3cc29ce308.jpg"
    }
  ],
  "foil_mask_url": "https://api.lorcana.ravensburger.com/images/fr/set2/masks/1468x2048/1_02d3a8d8b28924e39605971bc4ac095a4721756a.jpg",
  "card_sets": [
    2
  ],
  "magic_ink_colors": [
    "AMBER"
  ],
  "searchable_keywords": [
    "Blanche-Neige et les Sept Nains",
    "Snow White"
  ]
}