{
  "name": "Lezione d'Agguato",
  "rarity": "UNCOMMON",
  "ink_cost": 2,
  "author": "Moniek Schilder",
  "deck_building_id": "12f96e5edbcf8a1a75344eb8f5097aaec5b6c67a",
  "culture_invariant_id": 1840,
  "sort_number": 1838,
  "additional_info": [],
  "ink_convertible": true,
  "abilities": [],
  "subtypes": [],
  "flavor_text": "Guarda questo trucco pazzesco che mi ha insegnato mio papà!%—Simba",
  "rules_text": "Un personaggio a tua scelta riceve -2 per questo turno. Un tuo personaggio a tua scelta ottiene Sfuggente per questo turno. (Può sfidare altri personaggi con Sfuggente.)",
  "card_identifier": "176/204 IT 8",
  "image_urls": [
    {
      "height": 2048,
      "url": "https://api.lorcana.ravensburger.com/images/it/set8/cards/1468x2048/176_3124bd2229f8d2b0c6ab382150e481504620e8d3.jpg"
    },
    {
      "height": 512,
      "url": "https://api.lorcana.ravensburger.com/images/it/set8/cards/367x512/176_78ce11b3fddb2b1afd45a06449ba49fee1032588.jpg"
    }
  ],
  "foil_mask_url": "https://api.lorcana.ravensburger.com/images/it/set8/masks/1468x2048/176_15d02030e596a729592e847557271bd2b036539c.jpg",
  "card_sets": [
    8
  ],
  "magic_ink_colors": [
    "SAPPHIRE"
  ],
  "searchable_keywords": [
    "Lion King",
    "Il re leone"
  ]
}