{
  "name": "Dig a Little Deeper",
  "rarity": "UNCOMMON",
  "ink_cost": 8,
  "author": "Rachel Elese",
  "deck_building_id": "7532c69617d7ae6a280449248ba2db8345934f92",
  "culture_invariant_id": 853,
  "sort_number": 863,
  "additional_info": [],
  "ink_convertible": false,
  "abilities": [
    "Sing Together"
  ],
  "subtypes": [
    "Song"
  ],
  "flavor_text": "",
  "rules_text": "Sing Together 8 (Any number of your or your teammates’ characters with total cost 8 or more may to sing this song for free.) Look at the top 7 cards of your deck. Put 2 into your hand. Put the rest on the bottom of your deck in any order.",
  "card_identifier": "162/204 EN 4",
  "image_urls": [
    {
      "height": 2048,
      "url": "https://api.lorcana.ravensburger.com/images/en/set4/cards/1468x2048/162_0f260321e2406d6f7a510e3e365835f2fb8404fc.jpg"
    },
    {
      "height": 512,
      "url": "https://api.lorcana.ravensburger.com/images/en/set4/cards/367x512/162_8001b567041b910d3f26fd08e9bd47a1ca36bed5.jpg"
    }
  ],
  "foil_mask_url": "https://api.lorcana.ravensburger.com/images/en/set4/masks/1468x2048/162_b84f090c5eeca531cabf107a68c3c7f0335e7678.jpg",
  "card_sets": [
    4
  ],
  "magic_ink_colors": [
    "SAPPHIRE"
  ],
  "searchable_keywords": [
    "Princess and the Frog"
  ]
}